{
  "cheeses": [
    {
      "id": 1,
      "name": "cheddar",
      "firmness": "firm",
      "image": "https://bigoven-res.cloudinary.com/image/upload/h_640,w_640,c_fill/cheddar-cheese.jpg",
      "description": "Tangy and sharp, this cheese pairs well with apples and pears."
    },
    {
      "id": 2,
      "name": "mozzarella",
      "firmness": "soft",
      "image": "https://www.seriouseats.com/thmb/UvRcu5E4NpSitT6Zew8dwlZyYzA=/450x0/filters:no_upscale():max_bytes(150000):strip_icc()/__opt__aboutcom__coeus__resources__content_migration__serious_eats__seriouseats.com__recipes__images__2015__10__20151017-pies-vicky-wasik-2-6f491edb6065485a86d6af639a592298.jpg",
      "description": "This is a fresh, mild cheese, delicious with tomatoes and basil."
    },
    {
      "id": 3,
      "name": "swiss",
      "firmness": "firm",
      "image": "http://cdn.shopify.com/s/files/1/0360/3578/8938/products/slicedswiss_1024x.jpg?v=1618437421",
      "description": "This sharp, nutty cheese pairs well with cured meats and mustard."
    },
    {
      "id": 4,
      "name": "provolone",
      "firmness": "semi-firm",
      "image": "https://colosse.com/wp-content/uploads/2016/03/provolone-stock.jpg",
      "description": "This is a mild italian cheese."
    },
    {
      "id": 5,
      "name": "gouda",
      "firmness": "semi-firm",
      "image": "http://cdn.shopify.com/s/files/1/2836/2982/products/gouda_hero_grande.jpg?v=1529434181",
      "description": "This dutch-style cheese is a nutty, rich cheese that pairs beaufitully with sweet mustard and pickles."
    },
    {
      "id": 6,
      "name": "havarti",
      "firmness": "semi-firm",
      "image": "https://www.kroger.com/product/images/large/front/0020626500000",
      "description": "This is a mild, versatile cheese perfect for snacking or sandwiches."
    },
    {
      "id": 7,
      "name": "muenster",
      "firmness": "semi-soft",
      "image": "https://crownmarketonline.com/wp-content/uploads/2020/08/muenster-sliced.png",
      "description": "This orange-rinded classic is salty and mild."
    },
    {
      "id": 8,
      "name": "brie",
      "firmness": "soft",
      "image": "http://cdn.shopify.com/s/files/1/2836/2982/products/brie-recipe_grande.jpg?v=1533088694",
      "description": "This pungent french cheese is a wonderful addition to any cheese board."
    },
    {
      "id": 9,
      "name": "curds",
      "firmness": "semi-firm",
      "image": "https://www.tasteofhome.com/wp-content/uploads/2021/10/GettyImages-601149454.jpg",
      "description": "Known as squeaky cheese, these can be made from cheddar, muenster, or other cheeses, and are often flavored or deep fried."
    },
    {
      "id": 10,
      "name": "halloumi",
      "firmness": "semi-firm",
      "image": "https://images.immediate.co.uk/production/volatile/sites/30/2020/08/is-halloumi-healthy-guide-main-image-700-350-adb16c9.jpg?quality=90&resize=556,505",
      "description": "Halloumi is a young, salty cheese often grilled or fried and topped with herbs."
    },
    {
      "id": 11,
      "name": "chevre",
      "firmness": "soft",
      "image": "https://www.weedemandreap.com/wp-content/uploads/2014/09/IMG_9983-1.jpg",
      "description": "This is a soft, tangy goat cheese delicious with fruit and bread, or olive oil and herbs."
    },
    {
      "id": 12,
      "name": "feta",
      "firmness": "soft",
      "image": "https://post.healthline.com/wp-content/uploads/2020/08/Feta_Cheese_Good_or_Bad-732x549-thumbnail.jpg",
      "description": "This salty, tangy cheese can be made from sheep, goat, or cow milk."
    },
    {
      "id": 13,
      "name": "gruyere",
      "firmness": "firm",
      "image": "https://www.gourmetfoodworld.com/images/Product/medium/gormino-gruyere-cave-aged-12-months-1S-1506.jpg",
      "description": "This flavorful, buttery cheese pairs well with grapes and stonefruit."
    },
    {
      "id": 14,
      "name": "parmesan",
      "firmness": "firm",
      "image": "https://2rdnmg1qbg403gumla1v9i2h-wpengine.netdna-ssl.com/wp-content/uploads/sites/3/2021/08/ParmesanCheese-471343790-770x533-1-650x428.jpg",
      "description": "This aged, rinded cheese is crumbly and savory and pairs well with tangy and acidic foods like tomatoes."
    },
    {
      "id": 15,
      "name": "bleu",
      "firmness": "soft",
      "image": "https://www.lacademie.com/wp-content/uploads/2022/02/tasty-blue-cheese.jpg",
      "description": "This cheese is known for its pungent flavor and pairs well with dark chocolate and hazelnuts."
    },
    {
      "name": "danny",
      "firmness": "is",
      "image": "the",
      "description": "best",
      "id": 16
    },
    {
      "name": "maggie",
      "firmness": "is",
      "image": "maggie",
      "description": "is",
      "id": 17
    },
    {
      "name": "nick",
      "firmness": "is",
      "image": "nick",
      "description": "is",
      "id": 18
    }
  ]
}